doSql/__init__.py
doSql/sql.py
doSql-0.1.dist-info/METADATA
doSql-0.1.dist-info/WHEEL
doSql-0.1.dist-info/top_level.txt
doSql-0.1.dist-info/RECORD
