Metadata-Version: 2.1
Name: doSql
Version: 0.1
Summary: Подключение к БД
Home-page: https://github.com/saiyan05122004
Author: Ramzan Kadyrov
Author-email: ramzan095@gmail.com
Classifier: Programming Language :: Python :: 3
Classifier: License :: OSI Approved :: MIT License
Classifier: Operating System :: OS Independent
Requires-Python: >=3.6
